imkernel/__init__.py
imkernel/core/__init__.py
imkernel/core/model.py
imkernel/core/system.py
imkernel/utils/__init__.py
imkernel/utils/api_utils/__init__.py
imkernel/utils/api_utils/base.py
imkernel/utils/api_utils/client.py
imkernel/utils/api_utils/node.py
imkernel/utils/api_utils/project.py
imkernel/utils/api_utils/system.py
imkernel/utils/id_generator/__init__.py
imkernel/utils/id_generator/generator.py
imkernel/utils/id_generator/idregister.py
imkernel/utils/id_generator/options.py
imkernel/utils/id_generator/snowflake.py
imkernel/utils/id_generator/snowflake_m1.py
imkernel-2.2.0.dist-info/LICENSE
imkernel-2.2.0.dist-info/METADATA
imkernel-2.2.0.dist-info/WHEEL
imkernel-2.2.0.dist-info/top_level.txt
imkernel-2.2.0.dist-info/RECORD
