Metadata-Version: 2.1
Name: imkernel
Version: 2.2.0
Summary: imkernel for python
Author-email: ermeng <ermeng@ermeng.fun>
License:                     GNU GENERAL PUBLIC LICENSE
Project-URL: Homepage, https://github.com/MermengM/imkernel
Project-URL: Bug Tracker, https://github.com/MermengM/imkernel_python/issues
Keywords: IMKernel,kernel,IM,IL
Classifier: Operating System :: OS Independent
Classifier: Programming Language :: Python :: 3
Classifier: Programming Language :: Python :: 3.9
Requires-Python: >=3.9
License-File: LICENSE
Requires-Dist: pandas
Requires-Dist: loguru
Requires-Dist: requests
